nless/__init__.py
nless/autocomplete.py
nless/cli.py
nless/config.py
nless/delimiter.py
nless/gettingstarted.py
nless/help.py
nless/input.py
nless/nless.tcss
nless/nlessselect.py
nless/nlesstable.py
nless/types.py
nless/version.py
nothing_less-0.6.0.dist-info/METADATA
nothing_less-0.6.0.dist-info/WHEEL
nothing_less-0.6.0.dist-info/entry_points.txt
nothing_less-0.6.0.dist-info/licenses/LICENSE
nothing_less-0.6.0.dist-info/RECORD
