Metadata-Version: 2.4
Name: nothing-less
Version: 0.6.0
Summary: A TUI paging application with enhanced support for tabular data and real-time streaming
License-Expression: MIT
License-File: LICENSE
Author: Matt Pryor
Author-email: mapryor1991@yahoo.com
Requires-Python: >=3.13,<4.0
Classifier: Programming Language :: Python :: 3
Classifier: Programming Language :: Python :: 3.13
Classifier: Programming Language :: Python :: 3.14
Requires-Dist: pyperclip (>=1.11.0,<2.0.0)
Requires-Dist: textual (>=0.55.0)
Project-URL: Homepage, https://github.com/mpryor/nothing-less
Project-URL: Issues, https://github.com/mpryor/nothing-less/issues
